tikos/__init__.py
tikos/config.py
tikos/tikos.py
tikos/client/TikosClient.py
tikos/client/Tooling.py
tikos/client/__init__.py
tikos/client/client.py
tikos-0.3.1.dist-info/LICENSE
tikos-0.3.1.dist-info/METADATA
tikos-0.3.1.dist-info/WHEEL
tikos-0.3.1.dist-info/entry_points.txt
tikos-0.3.1.dist-info/top_level.txt
tikos-0.3.1.dist-info/RECORD
