Metadata-Version: 2.2
Name: tikos
Version: 0.3.1
Summary: Tikos Platform Library
Home-page: http://packages.python.org/tikos
Author: Don Liyanage, Tikos Technologies Ltd
Author-email: don.liyanage@tikos.tech
License: Apache-2.0
Keywords: Tikos
Classifier: Development Status :: 4 - Beta
Classifier: Topic :: Scientific/Engineering :: Artificial Intelligence
Classifier: License :: OSI Approved :: Apache Software License
License-File: LICENSE
Requires-Dist: requests
Dynamic: author
Dynamic: author-email
Dynamic: classifier
Dynamic: description
Dynamic: description-content-type
Dynamic: home-page
Dynamic: keywords
Dynamic: license
Dynamic: requires-dist
Dynamic: summary
